CHANGELOG.rst
MANIFEST.in
README.rst
setup.cfg
setup.py
arsenalweb/__init__.py
arsenalweb/models.py
arsenalweb/tests.py
arsenalweb.egg-info/PKG-INFO
arsenalweb.egg-info/SOURCES.txt
arsenalweb.egg-info/dependency_links.txt
arsenalweb.egg-info/entry_points.txt
arsenalweb.egg-info/not-zip-safe
arsenalweb.egg-info/requires.txt
arsenalweb.egg-info/top_level.txt
arsenalweb/db/arsenal-data.sql
arsenalweb/db/arsenal-schema.sql
arsenalweb/static/css/arsenal.css
arsenalweb/static/css/login.css
arsenalweb/static/css/node.css
arsenalweb/static/css/singleton.css
arsenalweb/static/css/test.css
arsenalweb/static/img/ajax-loader.gif
arsenalweb/static/img/checkbox_sheet.png
arsenalweb/static/img/drag-handle.png
arsenalweb/static/img/favico.png
arsenalweb/static/img/handle-h.png
arsenalweb/static/img/logo-blue-large.png
arsenalweb/static/img/logo-blue-medium.png
arsenalweb/static/img/logo-blue-small.png
arsenalweb/static/img/logo-l.png
arsenalweb/static/img/logo-s.png
arsenalweb/static/img/logo-white-large.png
arsenalweb/static/img/logo-white-medium.png
arsenalweb/static/img/logo-white-small.png
arsenalweb/static/img/mg.png
arsenalweb/static/img/nav-l.gif
arsenalweb/static/img/nav-le.gif
arsenalweb/static/img/nav-r.gif
arsenalweb/static/img/nav-re.gif
arsenalweb/static/img/select-arrow-down.png
arsenalweb/static/img/select-arrow-up.png
arsenalweb/static/img/select-arrow.png
arsenalweb/static/img/sf_in.png
arsenalweb/static/img/sf_out.png
arsenalweb/static/img/shield-s.png
arsenalweb/static/img/shield.png
arsenalweb/static/img/sort-a.png
arsenalweb/static/img/sort-ad.png
arsenalweb/static/img/sort-d.png
arsenalweb/static/js/Chart.min.js
arsenalweb/static/js/jquery-2.1.3.min.js
arsenalweb/static/js/jquery-ui.min.js
arsenalweb/static/js/jquery.barrating.min.js
arsenalweb/static/js/jquery.dragtable.js
arsenalweb/static/js/jquery.tablesorter.min.js
arsenalweb/static/js/resizable.js
arsenalweb/templates/global_layout.pt
arsenalweb/templates/global_layout2.pt
arsenalweb/templates/global_layout_multi-menu.pt
arsenalweb/templates/hardware_profile.pt
arsenalweb/templates/hardware_profiles.pt
arsenalweb/templates/help.pt
arsenalweb/templates/home.pt
arsenalweb/templates/home_pre.pt
arsenalweb/templates/login.pt
