Metadata-Version: 1.1
Name: arsenalweb
Version: 0.1
Summary: Arsenal web api/ui
Home-page: UNKNOWN
Author: Aaron Bandt
Author-email: aaron.bandt@citygridmedia.com
License: Apache
Keywords: Arsenal devops
Platform: UNKNOWN
Classifier: Programming Language :: Python
Classifier: Framework :: Pyramid
Classifier: Topic :: Internet :: WWW/HTTP
Classifier: Topic :: Internet :: WWW/HTTP :: WSGI :: Application
